LICENSE
chiff/__init__.py
chiff/api.py
chiff/constants.py
chiff/crypto.py
chiff/main.py
chiff/password_validator.py
chiff/queue_handler.py
chiff/session.py
chiff/setup.py
chiff/socket.py
chiff/ssh_key.py
chiff/utils.py
chiff-0.3.1.dist-info/LICENSE
chiff-0.3.1.dist-info/METADATA
chiff-0.3.1.dist-info/WHEEL
chiff-0.3.1.dist-info/entry_points.txt
chiff-0.3.1.dist-info/RECORD
