Metadata-Version: 2.1
Name: chiff
Version: 0.3.1
Summary: Chiff command-line client.
Home-page: https://chiff.app
License: GPL-3.0-or-later
Keywords: security,ssh,password
Author: bas-d
Author-email: 7903735+bas-d@users.noreply.github.com
Requires-Python: >=3.8.1,<4.0.0
Classifier: Development Status :: 3 - Alpha
Classifier: Environment :: Console
Classifier: License :: OSI Approved :: GNU General Public License v3 or later (GPLv3+)
Classifier: Operating System :: MacOS
Classifier: Operating System :: POSIX :: Linux
Classifier: Programming Language :: Python :: 3
Classifier: Programming Language :: Python :: 3.9
Classifier: Programming Language :: Python :: 3.10
Classifier: Programming Language :: Python :: 3.11
Classifier: Programming Language :: Python :: 3.12
Classifier: Topic :: Security
Classifier: Topic :: System :: Systems Administration
Requires-Dist: click (>=8.0,<9.0)
Requires-Dist: pillow (>=10.1.0,<11.0.0)
Requires-Dist: pykeepass (>=4.0,<5.0)
Requires-Dist: pynacl (>=1.4,<2.0)
Requires-Dist: python-daemon (>=3.0.1,<4.0.0)
Requires-Dist: qrcode (>=7.3.1,<8.0.0)
Requires-Dist: requests (>=2.2,<3.0)
Requires-Dist: tabulate (>=0.9.0,<0.10.0)
Requires-Dist: tldextract (>=5.1.2,<6.0.0)
Project-URL: Repository, https://github.com/chiff-app/chiff-cli
